terrys_toolbox/__init__.py
terrys_toolbox/exceptions.py
terrys_toolbox/rate_limiters.py
terrys_toolbox-0.1.2.dist-info/LICENSE
terrys_toolbox-0.1.2.dist-info/METADATA
terrys_toolbox-0.1.2.dist-info/WHEEL
terrys_toolbox-0.1.2.dist-info/RECORD
