Metadata-Version: 2.1
Name: terrys_toolbox
Version: 0.1.2
Summary: A toolbox package to hold various tools with utility beyond a single repo.
Home-page: https://github.com/tlg7c5/terrys-toolbox
Author: Terry Garner
Author-email: fterrylgarner@protonmail.com
Requires-Python: >=3.8,<4.0
Classifier: Programming Language :: Python :: 3
Classifier: Programming Language :: Python :: 3.8
Classifier: Programming Language :: Python :: 3.9
Classifier: Programming Language :: Python :: 3.10
Classifier: Programming Language :: Python :: 3.11
Project-URL: Documentation, https://tlg7c5.github.io/terrys-toolbox/
Project-URL: Repository, https://github.com/tlg7c5/terrys-toolbox
